marker/__init__.py
marker/marker.py
marker/settings.py
marker/commands/__init__.py
marker/commands/delete_reports.py
marker/commands/download.py
marker/commands/prepare.py
marker/commands/run.py
marker/commands/set_status.py
marker/commands/stats.py
marker/commands/upload_marks.py
marker/commands/upload_reports.py
marker/lms/__init__.py
marker/lms/base.py
marker/lms/canvas.py
marker/lms/markus.py
marker/repl/__init__.py
marker/repl/console.py
marker/repl/repl.py
marker/repl/show_stats.py
marker/utils/__init__.py
marker/utils/config.py
marker/utils/console.py
marker/utils/marksheet.py
marker/utils/report.py
marker/utils/tests.py
marker/utils/token.py
marker-2.1.5.dist-info/entry_points.txt
marker-2.1.5.dist-info/LICENSE
marker-2.1.5.dist-info/WHEEL
marker-2.1.5.dist-info/METADATA
marker-2.1.5.dist-info/RECORD
