Metadata-Version: 2.1
Name: marker
Version: 2.1.5
Summary: Marker: A highly configurable automarker for university assignments.
Home-page: https://github.com/mustafaquraish/marker
Author: Mustafa Quraish
Author-email: mustafa@cs.toronto.edu
Requires-Python: >=3.8
Classifier: License :: OSI Approved :: MIT License
Classifier: Environment :: Console
Classifier: Intended Audience :: Developers
Classifier: Programming Language :: Python :: 3
Classifier: Programming Language :: Python :: 3 :: Only
Classifier: Programming Language :: Python :: Implementation :: CPython
Classifier: Operating System :: Unix
Requires-Dist: aiofiles == 0.6.0
Requires-Dist: aiohttp == 3.7.4
Requires-Dist: cmd2 == 1.5.0
Requires-Dist: Jinja2 == 3.0.0
Requires-Dist: ruamel.yaml == 0.17.17
Requires-Dist: requests == 2.25.1
Requires-Dist: rich == 10.2.0
